protis/__about__.py
protis/__init__.py
protis/bands.py
protis/eig.py
protis/fft.py
protis/isocontour.py
protis/plot.py
protis/reduced.py
protis/simulation.py
protis/threed/__init__.py
protis/threed/lattice.py
protis/utils/__init__.py
protis/utils/helpers.py
protis/utils/jupyter.py
protis-1.0.0.dist-info/LICENSE.txt
protis-1.0.0.dist-info/METADATA
protis-1.0.0.dist-info/WHEEL
protis-1.0.0.dist-info/dependency_links.txt
protis-1.0.0.dist-info/top_level.txt
protis-1.0.0.dist-info/RECORD
