Metadata-Version: 2.1
Name: protis
Version: 1.0.0
Summary: Plane Wave Expansion method for photonic crystals
Home-page: https://gitlab.com/protis/protis
Author: Benjamin Vial
License: GPL-3.0-or-later
Project-URL: Code, https://gitlab.com/protis/protis
Project-URL: Documentation, https://protis.gitlab.io
Project-URL: Issues, https://gitlab.com/protis/protis/issues
Keywords: plane wave expansion,photonic crystals,metamaterials,band diagram
Classifier: Development Status :: 4 - Beta
Classifier: Intended Audience :: Science/Research
Classifier: License :: OSI Approved :: GNU General Public License v3 or later (GPLv3+)
Classifier: Operating System :: OS Independent
Classifier: Programming Language :: Python
Classifier: Programming Language :: Python :: 3
Classifier: Programming Language :: Python :: 3.6
Classifier: Programming Language :: Python :: 3.7
Classifier: Programming Language :: Python :: 3.8
Classifier: Programming Language :: Python :: 3.9
Classifier: Topic :: Scientific/Engineering
Classifier: Topic :: Scientific/Engineering :: Mathematics
Classifier: Topic :: Utilities
Requires-Python: >=3.6
License-File: LICENSE.txt
Requires-Dist: nannos >=2.6.0
Requires-Dist: scikit-image
Requires-Dist: pyvista[jupyter]
Provides-Extra: all
Requires-Dist: protis[backends] ; extra == 'all'
Requires-Dist: protis[gpu] ; extra == 'all'
Requires-Dist: protis[magma] ; extra == 'all'
Requires-Dist: protis[opt] ; extra == 'all'
Provides-Extra: backends
Requires-Dist: nannos[backends] ; extra == 'backends'
Provides-Extra: gpu
Requires-Dist: nannos[gpu] ; extra == 'gpu'
Provides-Extra: magma
Requires-Dist: nannos[magma] ; extra == 'magma'
Provides-Extra: opt
Requires-Dist: nlopt ; extra == 'opt'
